xrf_tomo/__init__.py
xrf_tomo/_version.py
xrf_tomo/tomo_scan.py
xrf_tomo/xrf_tomo_scaninfo.py
xrf_tomo/xrf_tomo_workflow.py
xrf_tomo/tests/__init__.py
xrf_tomo/tests/conftest.py
xrf_tomo/tests/test_imports.py
xrf_tomo/tests/test_workflow.py
xrf_tomo-0.1.2.dist-info/AUTHORS.rst
xrf_tomo-0.1.2.dist-info/LICENSE
xrf_tomo-0.1.2.dist-info/METADATA
xrf_tomo-0.1.2.dist-info/WHEEL
xrf_tomo-0.1.2.dist-info/entry_points.txt
xrf_tomo-0.1.2.dist-info/top_level.txt
xrf_tomo-0.1.2.dist-info/RECORD
