Metadata-Version: 2.1
Name: xrf-tomo
Version: 0.1.2
Summary: XRF Tomography Reconstruction
Home-page: https://github.com/dmgav/xrf-tomo
Author: Brookhaven National Lab
Author-email: 
License: BSD (3-clause)
Platform: UNKNOWN
Classifier: Development Status :: 2 - Pre-Alpha
Classifier: Natural Language :: English
Classifier: Programming Language :: Python :: 3
Requires-Python: >=3.7
License-File: LICENSE
License-File: AUTHORS.rst
Requires-Dist: h5py
Requires-Dist: numpy
Requires-Dist: pandas
Requires-Dist: scipy
